{"invoice_number":1,"date":"2024-10-13","details":[{"description":"Oil Change","quantity":1,"unit_price":150.0},{"description":"Brake Service","quantity":1,"unit_price":80.0}],"customer":{"id":1,"name":"Gabriel","phone":"123-456-7890"},"car":{"id":1,"model":"Kia Sentra","registration_number":"ABC1234"}},
{"invoice_number":1,"date":"2024-10-13","details":[{"description":"Oil Change","quantity":1,"unit_price":150.0},{"description":"Brake Service","quantity":1,"unit_price":80.0}],"customer":{"id":1,"name":"Gabriel","phone":"123-456-7890"},"car":{"id":1,"model":"Kia Sentra","registration_number":"ABC1234"}},
{"invoice_number":1,"date":"2024-10-13","details":[{"description":"Oil Change","quantity":1,"unit_price":150.0},{"description":"Brake Service","quantity":1,"unit_price":80.0}],"customer":{"id":1,"name":"Gabriel","phone":"123-456-7890"},"car":{"id":1,"model":"Kia Sentra","registration_number":"ABC1234"}},
{"invoice_number":1,"date":"2024-10-13","details":[{"description":"Oil Change","quantity":1,"unit_price":150.0},{"description":"Brake Service","quantity":1,"unit_price":80.0}],"customer":{"id":1,"name":"Gabriel","phone":"123-456-7890"},"car":{"id":1,"model":"Kia Sentra","registration_number":"ABC1234"}},
{"invoice_number":1,"date":"2024-10-13","details":[{"description":"Oil Change","quantity":1,"unit_price":150.0},{"description":"Brake Service","quantity":1,"unit_price":80.0}],"customer":{"id":1,"name":"Gabriel","phone":"123-456-7890"},"car":{"id":1,"model":"Kia Sentra","registration_number":"ABC1234"}},
{"invoice_number":1,"date":"2024-10-13","details":[{"description":"Oil Change","quantity":1,"unit_price":150.0},{"description":"Brake Service","quantity":1,"unit_price":80.0}],"customer":{"id":1,"name":"Gabriel","phone":"123-456-7890"},"car":{"id":1,"model":"Kia Sentra","registration_number":"ABC1234"}},
